LICENSE
README.rst
setup.py
corona_moova.egg-info/PKG-INFO
corona_moova.egg-info/SOURCES.txt
corona_moova.egg-info/dependency_links.txt
corona_moova.egg-info/requires.txt
corona_moova.egg-info/top_level.txt
moova/connector.py
moova/handler.py
moova/settings.py