Metadata-Version: 2.1
Name: corona-moova
Version: 1.0.2
Summary: Django Moova Integration
Home-page: https://gitlab.com/linets-projects/python-libraries/django-moova/
Author: Corona Development Team
Author-email: rolguin@corona.cl
License: MIT
Platform: UNKNOWN
Requires-Python: >=3.7
License-File: LICENSE
